package/__init__.py
homebill-0.0.1.dist-info/METADATA
homebill-0.0.1.dist-info/WHEEL
homebill-0.0.1.dist-info/top_level.txt
homebill-0.0.1.dist-info/RECORD
