Metadata-Version: 2.1
Name: homebill
Version: 0.0.1
Summary: for homtax sync
Home-page: https://github.com/sinit/homebill
Author: Sinan Soft
Author-email: sinit@sinit.co.kr
License: UNKNOWN
Download-URL: https://github.com/sinit/homebill/archive/master.zip
Keywords: homtax sync
Platform: UNKNOWN
Classifier: Programming Language :: Python :: 3
Classifier: Programming Language :: Python :: 3.2
Classifier: Programming Language :: Python :: 3.3
Classifier: Programming Language :: Python :: 3.4
Classifier: Programming Language :: Python :: 3.5
Classifier: Programming Language :: Python :: 3.6
Classifier: Programming Language :: Python :: 3.7
Requires-Python: >=3
